README.rst
setup.py
collective/__init__.py
collective.printview.egg-info/PKG-INFO
collective.printview.egg-info/SOURCES.txt
collective.printview.egg-info/dependency_links.txt
collective.printview.egg-info/entry_points.txt
collective.printview.egg-info/namespace_packages.txt
collective.printview.egg-info/not-zip-safe
collective.printview.egg-info/requires.txt
collective.printview.egg-info/top_level.txt
collective/printview/__init__.py
collective/printview/configure.zcml
collective/printview/controlpanel.py
collective/printview/interfaces.py
collective/printview/printview.py
collective/printview/vocabularies.py
collective/printview/locales/collective.printview.pot
collective/printview/locales/fi/LC_MESSAGES/collective.printview.po
collective/printview/printview_templates/printview.pt
collective/printview/profiles/default/actions.xml
collective/printview/profiles/default/browserlayer.xml
collective/printview/profiles/default/controlpanel.xml
collective/printview/profiles/default/metadata.xml
collective/printview/profiles/default/registry.xml
collective/printview/static/footnotelinks.js
collective/printview/static/print.css
collective/printview/static/printer-6.png
collective/printview/tests/__init__.py
collective/printview/tests/base.py
collective/printview/tests/testing.py
docs/HISTORY.txt