Metadata-Version: 1.0
Name: collective.printview
Version: 1.0.1
Summary: Displays all specified Plone content in one printable page.
Home-page: https://github.com/collective/collective.printview
Author: Jukka Ojaniemi
Author-email: jukka.ojaniemi@gmail.com
License: GPL
Keywords: collective.printview printview print
Platform: UNKNOWN
Classifier: Framework :: Plone
Classifier: Programming Language :: Python :: 2.6
Classifier: Programming Language :: Python :: 2.7
Classifier: Topic :: Software Development :: Libraries :: Python Modules
